gaussquad/__init__.py
gaussquad/_logging_utils.py
gaussquad/_moments.py
gaussquad/_validate_utils.py
gaussquad/gauss_quadrature.py
gaussquad-1.0.1.dist-info/licenses/LICENSE.txt
gaussquad-1.0.1.dist-info/METADATA
gaussquad-1.0.1.dist-info/WHEEL
gaussquad-1.0.1.dist-info/top_level.txt
gaussquad-1.0.1.dist-info/RECORD
