Metadata-Version: 2.4
Name: gaussquad
Version: 1.0.1
Summary: Compute Gauss quadrature nodes and weights for arbitrary weight functions.
Author: Mariia Steeghs-Turchina
License: Apache-2.0
Project-URL: Homepage, https://github.com/thatmariia/gaussquad
Project-URL: Documentation, https://thatmariia.github.io/gaussquad
Project-URL: Source, https://github.com/thatmariia/gaussquad
Keywords: gauss quadrature,numerical integration,golub-welsch
Classifier: Programming Language :: Python :: 3
Classifier: License :: OSI Approved :: Apache Software License
Classifier: Operating System :: OS Independent
Requires-Python: >=3.13
License-File: LICENSE.txt
Requires-Dist: numpy>=2.2.0
Requires-Dist: scipy>=1.15.0
Provides-Extra: dev
Requires-Dist: pytest; extra == "dev"
Requires-Dist: flake8; extra == "dev"
Requires-Dist: black; extra == "dev"
Requires-Dist: build; extra == "dev"
Provides-Extra: docs
Requires-Dist: sphinx; extra == "docs"
Requires-Dist: myst-parser; extra == "docs"
Requires-Dist: sphinx-book-theme; extra == "docs"
Dynamic: license-file
